{
  "families" : [{
      "id" : 63,
      "lastName" : "Bucolo",
      "members" : [61, 65, 66, 67, 68, 72, 73, 74, 83, 84, 92, 97, 104]
    }, {
      "id" : 65,
      "lastName" : "Mayhorn",
      "members" : [62]
    }, {
      "id" : 66,
      "lastName" : "Salone",
      "members" : [63]
    }, {
      "id" : 67,
      "lastName" : "Flair",
      "members" : [64]
    }, {
      "id" : 68,
      "lastName" : "Lehew",
      "members" : [65]
    }, {
      "id" : 72,
      "lastName" : "Shomo",
      "members" : [69, 67, 75, 76, 77, 80, 88, 89, 91, 92, 113, 119, 120, 121, 131, 135, 154, 155, 156]
    }, {
      "id" : 73,
      "lastName" : "Muramoto",
      "members" : [70, 68, 80, 81, 82, 90, 93, 94, 95, 96, 87, 99, 100, 101, 107, 126]
    }, {
      "id" : 74,
      "lastName" : "Siegal",
      "members" : [71, 111, 114, 115, 116, 125, 126, 127, 128, 119, 133, 134, 91, 145, 146, 147]
    }, {
      "id" : 75,
      "lastName" : "Domingez",
      "members" : [72]
    }, {
      "id" : 81,
      "lastName" : "Chatt",
      "members" : [78]
    }, {
      "id" : 82,
      "lastName" : "Millon",
      "members" : [79]
    }, {
      "id" : 86,
      "lastName" : "Ales",
      "members" : [83]
    }, {
      "id" : 88,
      "lastName" : "Warpool",
      "members" : [85, 74, 86, 87, 95, 98]
    }, {
      "id" : 92,
      "lastName" : "Sawrey",
      "members" : [89]
    }, {
      "id" : 93,
      "lastName" : "Cairo",
      "members" : [90]
    }, {
      "id" : 97,
      "lastName" : "Inga",
      "members" : [94]
    }, {
      "id" : 105,
      "lastName" : "Sunderlin",
      "members" : [102, 88, 103]
    }, {
      "id" : 108,
      "lastName" : "Sheehy",
      "members" : [105]
    }, {
      "id" : 109,
      "lastName" : "Pizzano",
      "members" : [106, 123, 139, 140, 141]
    }, {
      "id" : 111,
      "lastName" : "Pyros",
      "members" : [108, 109, 110, 111, 112, 79, 113, 117, 118]
    }, {
      "id" : 113,
      "lastName" : "Rotella",
      "members" : [109]
    }, {
      "id" : 121,
      "lastName" : "Flenard",
      "members" : [117]
    }, {
      "id" : 126,
      "lastName" : "Shakin",
      "members" : [122, 114, 123, 124, 105, 142, 143, 144]
    }, {
      "id" : 129,
      "lastName" : "Violetta",
      "members" : [125]
    }, {
      "id" : 133,
      "lastName" : "Kaplan",
      "members" : [129, 118, 130, 131, 132, 121, 136, 137, 138, 151, 152]
    }, {
      "id" : 152,
      "lastName" : "Harres",
      "members" : [148]
    }, {
      "id" : 153,
      "lastName" : "Lababit",
      "members" : [149]
    }, {
      "id" : 154,
      "lastName" : "Kratochwil",
      "members" : [150]
    }, {
      "id" : 157,
      "lastName" : "Symmes",
      "members" : [153, 132, 157]
    }],
  "persons" : [{
      "age" : 95,
      "alive" : false,
      "children" : [66, 67, 68],
      "faction" : {
        "id" : 1,
        "occupation" : "huntsman",
        "title" : "Hunters"
      },
      "family" : 63,
      "friends" : [62, 63, 64],
      "gender" : true,
      "generation" : 4,
      "id" : 61,
      "lastName" : "Bucolo",
      "name" : "Abe",
      "origFamily" : 63,
      "parents" : [],
      "spouse" : 65
    }, {
      "age" : 86,
      "alive" : true,
      "children" : [],
      "family" : 65,
      "friends" : [61, 65],
      "gender" : true,
      "generation" : 4,
      "id" : 62,
      "lastName" : "Mayhorn",
      "name" : "Ben",
      "origFamily" : 65,
      "parents" : [],
      "spouse" : -1
    }, {
      "age" : 82,
      "alive" : false,
      "children" : [],
      "family" : 66,
      "friends" : [61, 65],
      "gender" : true,
      "generation" : 4,
      "id" : 63,
      "lastName" : "Salone",
      "name" : "Howard",
      "origFamily" : 66,
      "parents" : [],
      "spouse" : -1
    }, {
      "age" : 98,
      "alive" : false,
      "children" : [],
      "family" : 67,
      "friends" : [61, 65, 108, 109],
      "gender" : true,
      "generation" : 4,
      "id" : 64,
      "lastName" : "Flair",
      "name" : "Floyd",
      "origFamily" : 67,
      "parents" : [],
      "spouse" : -1
    }, {
      "age" : 93,
      "alive" : false,
      "children" : [66, 67, 68],
      "faction" : {
        "id" : 0,
        "occupation" : "plowman",
        "title" : "Farmers"
      },
      "family" : 63,
      "friends" : [62, 63, 64],
      "gender" : false,
      "generation" : 4,
      "id" : 65,
      "lastName" : "Bucolo",
      "name" : "Eunice",
      "origFamily" : 68,
      "parents" : [],
      "spouse" : 61
    }, {
      "age" : 77,
      "alive" : true,
      "children" : [73, 74],
      "faction" : {
        "id" : 2,
        "occupation" : "perfumer",
        "title" : "Craftsmen"
      },
      "family" : 63,
      "friends" : [69, 70, 71, 111],
      "gender" : true,
      "generation" : 3,
      "id" : 66,
      "lastName" : "Bucolo",
      "name" : "George",
      "origFamily" : 63,
      "parents" : [61, 65],
      "spouse" : 72
    }, {
      "age" : 68,
      "alive" : true,
      "children" : [75, 76, 77],
      "faction" : {
        "id" : 1,
        "occupation" : "gamekeeper",
        "title" : "Hunters"
      },
      "family" : 72,
      "friends" : [70, 69, 68, 111, 71],
      "gender" : false,
      "generation" : 3,
      "id" : 67,
      "lastName" : "Shomo",
      "name" : "Christine",
      "origFamily" : 63,
      "parents" : [61, 65],
      "spouse" : 69
    }, {
      "age" : 77,
      "alive" : true,
      "children" : [80, 81, 82],
      "faction" : {
        "id" : 0,
        "occupation" : "plowman",
        "title" : "Farmers"
      },
      "family" : 73,
      "friends" : [69, 71, 67, 70, 111],
      "gender" : false,
      "generation" : 3,
      "id" : 68,
      "lastName" : "Muramoto",
      "name" : "Janet",
      "origFamily" : 63,
      "parents" : [61, 65],
      "spouse" : 70
    }, {
      "age" : 69,
      "alive" : true,
      "children" : [75, 76, 77],
      "faction" : {
        "id" : 2,
        "occupation" : "compasssmith",
        "title" : "Craftsmen"
      },
      "family" : 72,
      "friends" : [66, 72, 67, 68, 70],
      "gender" : true,
      "generation" : 3,
      "id" : 69,
      "lastName" : "Shomo",
      "name" : "Leon",
      "origFamily" : 72,
      "parents" : [],
      "spouse" : 67
    }, {
      "age" : 79,
      "alive" : false,
      "children" : [80, 81, 82],
      "faction" : {
        "id" : 1,
        "occupation" : "hunter",
        "title" : "Hunters"
      },
      "family" : 73,
      "friends" : [66, 72, 67, 69, 68, 71, 78, 79],
      "gender" : true,
      "generation" : 3,
      "id" : 70,
      "lastName" : "Muramoto",
      "name" : "Richard",
      "origFamily" : 73,
      "parents" : [],
      "spouse" : 68
    }, {
      "age" : 61,
      "alive" : false,
      "children" : [114, 115, 116],
      "faction" : {
        "id" : 0,
        "occupation" : "ackerman",
        "title" : "Farmers"
      },
      "family" : 74,
      "friends" : [66, 72, 68, 70, 110, 67],
      "gender" : true,
      "generation" : 3,
      "id" : 71,
      "lastName" : "Siegal",
      "name" : "Millard",
      "origFamily" : 74,
      "parents" : [],
      "spouse" : 111
    }, {
      "age" : 66,
      "alive" : false,
      "children" : [73, 74],
      "faction" : {
        "id" : 0,
        "occupation" : "tillerman",
        "title" : "Farmers"
      },
      "family" : 63,
      "friends" : [70, 71, 69, 110, 79],
      "gender" : false,
      "generation" : 3,
      "id" : 72,
      "lastName" : "Bucolo",
      "name" : "Clara",
      "origFamily" : 75,
      "parents" : [],
      "spouse" : 66
    }, {
      "age" : 50,
      "alive" : false,
      "children" : [84],
      "faction" : {
        "id" : 2,
        "occupation" : "perfumer",
        "title" : "Craftsmen"
      },
      "family" : 63,
      "friends" : [81, 75, 80, 89, 90],
      "gender" : true,
      "generation" : 2,
      "id" : 73,
      "lastName" : "Bucolo",
      "name" : "Clarence",
      "origFamily" : 63,
      "parents" : [66, 72],
      "spouse" : 83
    }, {
      "age" : 48,
      "alive" : true,
      "children" : [86, 87],
      "faction" : {
        "id" : 0,
        "occupation" : "tillerman",
        "title" : "Farmers"
      },
      "family" : 88,
      "friends" : [81, 75, 76, 80, 77],
      "gender" : false,
      "generation" : 2,
      "id" : 74,
      "lastName" : "Warpool",
      "name" : "Annie",
      "origFamily" : 63,
      "parents" : [66, 72],
      "spouse" : 85
    }, {
      "age" : 49,
      "alive" : true,
      "children" : [119, 120, 121],
      "faction" : {
        "id" : 2,
        "occupation" : "clothier",
        "title" : "Craftsmen"
      },
      "family" : 72,
      "friends" : [83, 85, 80, 73, 74, 114],
      "gender" : true,
      "generation" : 2,
      "id" : 75,
      "lastName" : "Shomo",
      "name" : "Oliver",
      "origFamily" : 72,
      "parents" : [67, 69],
      "spouse" : 113
    }, {
      "age" : 42,
      "alive" : false,
      "children" : [88],
      "faction" : {
        "id" : 1,
        "occupation" : "gamekeeper",
        "title" : "Hunters"
      },
      "family" : 72,
      "friends" : [80, 74, 90, 82, 94],
      "gender" : true,
      "generation" : 2,
      "id" : 76,
      "lastName" : "Shomo",
      "name" : "Russell",
      "origFamily" : 72,
      "parents" : [67, 69],
      "spouse" : 80
    }, {
      "age" : 52,
      "alive" : false,
      "children" : [91, 92],
      "faction" : {
        "id" : 1,
        "occupation" : "hunter",
        "title" : "Hunters"
      },
      "family" : 72,
      "friends" : [83, 85, 82, 74, 90],
      "gender" : true,
      "generation" : 2,
      "id" : 77,
      "lastName" : "Shomo",
      "name" : "Gilbert",
      "origFamily" : 72,
      "parents" : [67, 69],
      "spouse" : 89
    }, {
      "age" : 77,
      "alive" : false,
      "children" : [],
      "family" : 81,
      "friends" : [70, 110, 79, 112, 117],
      "gender" : true,
      "generation" : 3,
      "id" : 78,
      "lastName" : "Chatt",
      "name" : "Lyle",
      "origFamily" : 81,
      "parents" : [],
      "spouse" : -1
    }, {
      "age" : 63,
      "alive" : true,
      "children" : [113],
      "faction" : {
        "id" : 0,
        "occupation" : "sheepshearer",
        "title" : "Farmers"
      },
      "family" : 111,
      "friends" : [70, 78, 72],
      "gender" : false,
      "generation" : 3,
      "id" : 79,
      "lastName" : "Pyros",
      "name" : "Shirley",
      "origFamily" : 82,
      "parents" : [],
      "spouse" : 110
    }, {
      "age" : 50,
      "alive" : false,
      "children" : [88],
      "faction" : {
        "id" : 1,
        "occupation" : "hunter",
        "title" : "Hunters"
      },
      "family" : 72,
      "friends" : [75, 76, 74, 73, 85, 82, 90],
      "gender" : false,
      "generation" : 2,
      "id" : 80,
      "lastName" : "Shomo",
      "name" : "Shirley",
      "origFamily" : 73,
      "parents" : [68, 70],
      "spouse" : 76
    }, {
      "age" : 59,
      "alive" : true,
      "children" : [93],
      "faction" : {
        "id" : 0,
        "occupation" : "plowman",
        "title" : "Farmers"
      },
      "family" : 73,
      "friends" : [73, 83, 74, 89, 90],
      "gender" : true,
      "generation" : 2,
      "id" : 81,
      "lastName" : "Muramoto",
      "name" : "Lyle",
      "origFamily" : 73,
      "parents" : [68, 70],
      "spouse" : 90
    }, {
      "age" : 56,
      "alive" : true,
      "children" : [95, 96],
      "faction" : {
        "id" : 0,
        "occupation" : "plowman",
        "title" : "Farmers"
      },
      "family" : 73,
      "friends" : [83, 85, 77, 89, 80, 76, 94],
      "gender" : true,
      "generation" : 2,
      "id" : 82,
      "lastName" : "Muramoto",
      "name" : "Herman",
      "origFamily" : 73,
      "parents" : [68, 70],
      "spouse" : 94
    }, {
      "age" : 58,
      "alive" : true,
      "children" : [84],
      "faction" : {
        "id" : 1,
        "occupation" : "falconer",
        "title" : "Hunters"
      },
      "family" : 63,
      "friends" : [82, 75, 81, 85, 77],
      "gender" : false,
      "generation" : 2,
      "id" : 83,
      "lastName" : "Bucolo",
      "name" : "Theresa",
      "origFamily" : 86,
      "parents" : [],
      "spouse" : 73
    }, {
      "age" : 26,
      "alive" : true,
      "children" : [97, 104],
      "faction" : {
        "id" : 2,
        "occupation" : "perfumer",
        "title" : "Craftsmen"
      },
      "family" : 63,
      "friends" : [86, 93, 91, 95, 88, 87, 102, 96],
      "gender" : true,
      "generation" : 1,
      "id" : 84,
      "lastName" : "Bucolo",
      "name" : "Irving",
      "origFamily" : 63,
      "parents" : [73, 83],
      "spouse" : 92
    }, {
      "age" : 50,
      "alive" : true,
      "children" : [86, 87],
      "faction" : {
        "id" : 2,
        "occupation" : "lampwright",
        "title" : "Craftsmen"
      },
      "family" : 88,
      "friends" : [83, 82, 75, 80, 77],
      "gender" : true,
      "generation" : 2,
      "id" : 85,
      "lastName" : "Warpool",
      "name" : "Robert",
      "origFamily" : 88,
      "parents" : [],
      "spouse" : 74
    }, {
      "age" : 21,
      "alive" : true,
      "children" : [98],
      "faction" : {
        "id" : 0,
        "occupation" : "tillerman",
        "title" : "Farmers"
      },
      "family" : 88,
      "friends" : [84, 93, 91, 92, 87],
      "gender" : true,
      "generation" : 1,
      "id" : 86,
      "lastName" : "Warpool",
      "name" : "Victor",
      "origFamily" : 88,
      "parents" : [74, 85],
      "spouse" : 95
    }, {
      "age" : 32,
      "alive" : true,
      "children" : [99, 100, 101, 107],
      "faction" : {
        "id" : 2,
        "occupation" : "lampwright",
        "title" : "Craftsmen"
      },
      "family" : 73,
      "friends" : [91, 88, 84, 86, 105, 102],
      "gender" : false,
      "generation" : 1,
      "id" : 87,
      "lastName" : "Muramoto",
      "name" : "Cora",
      "origFamily" : 88,
      "parents" : [74, 85],
      "spouse" : 93
    }, {
      "age" : 26,
      "alive" : false,
      "children" : [103],
      "faction" : {
        "id" : 0,
        "occupation" : "cowherd",
        "title" : "Farmers"
      },
      "family" : 105,
      "friends" : [95, 87, 96, 84, 92],
      "gender" : false,
      "generation" : 1,
      "id" : 88,
      "lastName" : "Sunderlin",
      "name" : "Velma",
      "origFamily" : 72,
      "parents" : [76, 80],
      "spouse" : 102
    }, {
      "age" : 57,
      "alive" : true,
      "children" : [91, 92],
      "faction" : {
        "id" : 2,
        "occupation" : "billier",
        "title" : "Craftsmen"
      },
      "family" : 72,
      "friends" : [81, 82, 73, 90, 94],
      "gender" : false,
      "generation" : 2,
      "id" : 89,
      "lastName" : "Shomo",
      "name" : "Theresa",
      "origFamily" : 92,
      "parents" : [],
      "spouse" : 77
    }, {
      "age" : 55,
      "alive" : false,
      "children" : [93],
      "faction" : {
        "id" : 1,
        "occupation" : "huntsman",
        "title" : "Hunters"
      },
      "family" : 73,
      "friends" : [89, 80, 81, 77, 76, 73],
      "gender" : false,
      "generation" : 2,
      "id" : 90,
      "lastName" : "Muramoto",
      "name" : "Fannie",
      "origFamily" : 93,
      "parents" : [],
      "spouse" : 81
    }, {
      "age" : 36,
      "alive" : false,
      "children" : [145],
      "faction" : {
        "id" : 2,
        "occupation" : "horner",
        "title" : "Craftsmen"
      },
      "family" : 74,
      "friends" : [84, 86, 87, 102, 93, 96, 131, 120, 106],
      "gender" : false,
      "generation" : 1,
      "id" : 91,
      "lastName" : "Siegal",
      "name" : "Ruth",
      "origFamily" : 72,
      "parents" : [77, 89],
      "spouse" : 127
    }, {
      "age" : 36,
      "alive" : true,
      "children" : [97, 104],
      "faction" : {
        "id" : 2,
        "occupation" : "billier",
        "title" : "Craftsmen"
      },
      "family" : 63,
      "friends" : [96, 86, 95, 93, 88],
      "gender" : false,
      "generation" : 1,
      "id" : 92,
      "lastName" : "Bucolo",
      "name" : "Celia",
      "origFamily" : 72,
      "parents" : [77, 89],
      "spouse" : 84
    }, {
      "age" : 38,
      "alive" : false,
      "children" : [99, 100, 101, 107],
      "faction" : {
        "id" : 0,
        "occupation" : "plowman",
        "title" : "Farmers"
      },
      "family" : 73,
      "friends" : [84, 86, 95, 92, 91, 102, 105, 106],
      "gender" : true,
      "generation" : 1,
      "id" : 93,
      "lastName" : "Muramoto",
      "name" : "Elbert",
      "origFamily" : 73,
      "parents" : [81, 90],
      "spouse" : 87
    }, {
      "age" : 45,
      "alive" : true,
      "children" : [95, 96],
      "faction" : {
        "id" : 0,
        "occupation" : "sheepshearer",
        "title" : "Farmers"
      },
      "family" : 73,
      "friends" : [82, 76, 89, 114, 122],
      "gender" : false,
      "generation" : 2,
      "id" : 94,
      "lastName" : "Muramoto",
      "name" : "Lenora",
      "origFamily" : 97,
      "parents" : [],
      "spouse" : 82
    }, {
      "age" : 29,
      "alive" : false,
      "children" : [98],
      "faction" : {
        "id" : 0,
        "occupation" : "sheepshearer",
        "title" : "Farmers"
      },
      "family" : 88,
      "friends" : [84, 88, 93, 92, 102, 106],
      "gender" : false,
      "generation" : 1,
      "id" : 95,
      "lastName" : "Warpool",
      "name" : "June",
      "origFamily" : 73,
      "parents" : [82, 94],
      "spouse" : 86
    }, {
      "age" : 29,
      "alive" : true,
      "children" : [],
      "faction" : {
        "id" : 0,
        "occupation" : "plowman",
        "title" : "Farmers"
      },
      "family" : 73,
      "friends" : [92, 88, 91, 84, 105, 106, 119, 120],
      "gender" : true,
      "generation" : 1,
      "id" : 96,
      "lastName" : "Muramoto",
      "name" : "Rudolph",
      "origFamily" : 73,
      "parents" : [82, 94],
      "spouse" : 126
    }, {
      "age" : 10,
      "alive" : true,
      "children" : [],
      "family" : 63,
      "friends" : [],
      "gender" : false,
      "generation" : 0,
      "id" : 97,
      "lastName" : "Bucolo",
      "name" : "Verna",
      "origFamily" : 63,
      "parents" : [84, 92],
      "spouse" : -1
    }, {
      "age" : 5,
      "alive" : true,
      "children" : [],
      "family" : 88,
      "friends" : [],
      "gender" : true,
      "generation" : 0,
      "id" : 98,
      "lastName" : "Warpool",
      "name" : "Franklin",
      "origFamily" : 88,
      "parents" : [86, 95],
      "spouse" : -1
    }, {
      "age" : 6,
      "alive" : true,
      "children" : [],
      "family" : 73,
      "friends" : [],
      "gender" : false,
      "generation" : 0,
      "id" : 99,
      "lastName" : "Muramoto",
      "name" : "Pearl",
      "origFamily" : 73,
      "parents" : [87, 93],
      "spouse" : -1
    }, {
      "age" : 4,
      "alive" : true,
      "children" : [],
      "family" : 73,
      "friends" : [],
      "gender" : true,
      "generation" : 0,
      "id" : 100,
      "lastName" : "Muramoto",
      "name" : "Adolph",
      "origFamily" : 73,
      "parents" : [87, 93],
      "spouse" : -1
    }, {
      "age" : 3,
      "alive" : true,
      "children" : [],
      "family" : 73,
      "friends" : [],
      "gender" : true,
      "generation" : 0,
      "id" : 101,
      "lastName" : "Muramoto",
      "name" : "Louis",
      "origFamily" : 73,
      "parents" : [87, 93],
      "spouse" : -1
    }, {
      "age" : 35,
      "alive" : false,
      "children" : [103],
      "faction" : {
        "id" : 0,
        "occupation" : "gardener",
        "title" : "Farmers"
      },
      "family" : 105,
      "friends" : [95, 91, 84, 93, 87],
      "gender" : true,
      "generation" : 1,
      "id" : 102,
      "lastName" : "Sunderlin",
      "name" : "Millard",
      "origFamily" : 105,
      "parents" : [],
      "spouse" : 88
    }, {
      "age" : 6,
      "alive" : true,
      "children" : [],
      "family" : 105,
      "friends" : [],
      "gender" : false,
      "generation" : 0,
      "id" : 103,
      "lastName" : "Sunderlin",
      "name" : "Loretta",
      "origFamily" : 105,
      "parents" : [88, 102],
      "spouse" : -1
    }, {
      "age" : 4,
      "alive" : false,
      "children" : [],
      "family" : 63,
      "friends" : [],
      "gender" : false,
      "generation" : 0,
      "id" : 104,
      "lastName" : "Bucolo",
      "name" : "Rachel",
      "origFamily" : 63,
      "parents" : [92, 84],
      "spouse" : -1
    }, {
      "age" : 40,
      "alive" : true,
      "children" : [142, 143, 144],
      "faction" : {
        "id" : 0,
        "occupation" : "dung carter",
        "title" : "Farmers"
      },
      "family" : 126,
      "friends" : [93, 87, 96, 131, 132, 119],
      "gender" : false,
      "generation" : 1,
      "id" : 105,
      "lastName" : "Shakin",
      "name" : "Verna",
      "origFamily" : 108,
      "parents" : [],
      "spouse" : 124
    }, {
      "age" : 28,
      "alive" : true,
      "children" : [139, 140, 141],
      "faction" : {
        "id" : 1,
        "occupation" : "trapper",
        "title" : "Hunters"
      },
      "family" : 109,
      "friends" : [93, 95, 96, 132, 91],
      "gender" : true,
      "generation" : 1,
      "id" : 106,
      "lastName" : "Pizzano",
      "name" : "Arthur",
      "origFamily" : 109,
      "parents" : [],
      "spouse" : 123
    }, {
      "age" : 8,
      "alive" : true,
      "children" : [],
      "family" : 73,
      "friends" : [],
      "gender" : true,
      "generation" : 0,
      "id" : 107,
      "lastName" : "Muramoto",
      "name" : "Edwin",
      "origFamily" : 73,
      "parents" : [93, 87],
      "spouse" : -1
    }, {
      "age" : 83,
      "alive" : false,
      "children" : [110, 111, 112],
      "faction" : {
        "id" : 2,
        "occupation" : "rectifier",
        "title" : "Craftsmen"
      },
      "family" : 111,
      "friends" : [64],
      "gender" : true,
      "generation" : 4,
      "id" : 108,
      "lastName" : "Pyros",
      "name" : "Daniel",
      "origFamily" : 111,
      "parents" : [],
      "spouse" : 109
    }, {
      "age" : 95,
      "alive" : false,
      "children" : [110, 111, 112],
      "faction" : {
        "id" : 1,
        "occupation" : "rat catcher",
        "title" : "Hunters"
      },
      "family" : 111,
      "friends" : [64],
      "gender" : false,
      "generation" : 4,
      "id" : 109,
      "lastName" : "Pyros",
      "name" : "Minnie",
      "origFamily" : 113,
      "parents" : [],
      "spouse" : 108
    }, {
      "age" : 67,
      "alive" : false,
      "children" : [113],
      "faction" : {
        "id" : 2,
        "occupation" : "rectifier",
        "title" : "Craftsmen"
      },
      "family" : 111,
      "friends" : [78, 71, 72],
      "gender" : true,
      "generation" : 3,
      "id" : 110,
      "lastName" : "Pyros",
      "name" : "Forrest",
      "origFamily" : 111,
      "parents" : [108, 109],
      "spouse" : 79
    }, {
      "age" : 67,
      "alive" : true,
      "children" : [114, 115, 116],
      "faction" : {
        "id" : 2,
        "occupation" : "combmaker",
        "title" : "Craftsmen"
      },
      "family" : 74,
      "friends" : [67, 68, 66, 112, 117],
      "gender" : false,
      "generation" : 3,
      "id" : 111,
      "lastName" : "Siegal",
      "name" : "Amelia",
      "origFamily" : 111,
      "parents" : [108, 109],
      "spouse" : 71
    }, {
      "age" : 67,
      "alive" : true,
      "children" : [118],
      "faction" : {
        "id" : 2,
        "occupation" : "rectifier",
        "title" : "Craftsmen"
      },
      "family" : 111,
      "friends" : [111, 78],
      "gender" : true,
      "generation" : 3,
      "id" : 112,
      "lastName" : "Pyros",
      "name" : "Edgar",
      "origFamily" : 111,
      "parents" : [108, 109],
      "spouse" : 117
    }, {
      "age" : 47,
      "alive" : false,
      "children" : [119, 120, 121],
      "faction" : {
        "id" : 0,
        "occupation" : "sheepshearer",
        "title" : "Farmers"
      },
      "family" : 72,
      "friends" : [114, 116, 115, 125, 118],
      "gender" : false,
      "generation" : 2,
      "id" : 113,
      "lastName" : "Shomo",
      "name" : "Sophia",
      "origFamily" : 111,
      "parents" : [110, 79],
      "spouse" : 75
    }, {
      "age" : 41,
      "alive" : false,
      "children" : [123, 124],
      "faction" : {
        "id" : 0,
        "occupation" : "ackerman",
        "title" : "Farmers"
      },
      "family" : 126,
      "friends" : [113, 75, 118, 94, 122],
      "gender" : false,
      "generation" : 2,
      "id" : 114,
      "lastName" : "Shakin",
      "name" : "Sarah",
      "origFamily" : 74,
      "parents" : [111, 71],
      "spouse" : 122
    }, {
      "age" : 45,
      "alive" : false,
      "children" : [126, 127, 128],
      "faction" : {
        "id" : 2,
        "occupation" : "combmaker",
        "title" : "Craftsmen"
      },
      "family" : 74,
      "friends" : [113, 122, 118],
      "gender" : true,
      "generation" : 2,
      "id" : 115,
      "lastName" : "Siegal",
      "name" : "Francis",
      "origFamily" : 74,
      "parents" : [111, 71],
      "spouse" : 125
    }, {
      "age" : 45,
      "alive" : false,
      "children" : [],
      "faction" : {
        "id" : 0,
        "occupation" : "ackerman",
        "title" : "Farmers"
      },
      "family" : 74,
      "friends" : [113, 118, 122, 129],
      "gender" : false,
      "generation" : 2,
      "id" : 116,
      "lastName" : "Siegal",
      "name" : "Amelia",
      "origFamily" : 74,
      "parents" : [111, 71],
      "spouse" : -1
    }, {
      "age" : 73,
      "alive" : true,
      "children" : [118],
      "faction" : {
        "id" : 0,
        "occupation" : "horse trainer",
        "title" : "Farmers"
      },
      "family" : 111,
      "friends" : [78, 111],
      "gender" : false,
      "generation" : 3,
      "id" : 117,
      "lastName" : "Pyros",
      "name" : "Miriam",
      "origFamily" : 121,
      "parents" : [],
      "spouse" : 112
    }, {
      "age" : 51,
      "alive" : true,
      "children" : [130, 131, 132],
      "faction" : {
        "id" : 0,
        "occupation" : "horse trainer",
        "title" : "Farmers"
      },
      "family" : 133,
      "friends" : [114, 116, 113, 115],
      "gender" : false,
      "generation" : 2,
      "id" : 118,
      "lastName" : "Kaplan",
      "name" : "Anna",
      "origFamily" : 111,
      "parents" : [112, 117],
      "spouse" : 129
    }, {
      "age" : 31,
      "alive" : true,
      "children" : [133, 134, 146, 147],
      "faction" : {
        "id" : 2,
        "occupation" : "marleywoman",
        "title" : "Craftsmen"
      },
      "family" : 74,
      "friends" : [127, 123, 126, 105, 96, 131, 121],
      "gender" : false,
      "generation" : 1,
      "id" : 119,
      "lastName" : "Siegal",
      "name" : "Miriam",
      "origFamily" : 72,
      "parents" : [113, 75],
      "spouse" : 128
    }, {
      "age" : 31,
      "alive" : true,
      "children" : [135, 154, 155, 156],
      "faction" : {
        "id" : 0,
        "occupation" : "sheepshearer",
        "title" : "Farmers"
      },
      "family" : 72,
      "friends" : [128, 131, 96, 127, 91, 148, 150],
      "gender" : true,
      "generation" : 1,
      "id" : 120,
      "lastName" : "Shomo",
      "name" : "August",
      "origFamily" : 72,
      "parents" : [113, 75],
      "spouse" : 131
    }, {
      "age" : 27,
      "alive" : true,
      "children" : [136, 137, 138, 151, 152],
      "faction" : {
        "id" : 2,
        "occupation" : "clothier",
        "title" : "Craftsmen"
      },
      "family" : 133,
      "friends" : [124, 128, 119, 148, 149, 150],
      "gender" : false,
      "generation" : 1,
      "id" : 121,
      "lastName" : "Kaplan",
      "name" : "Caroline",
      "origFamily" : 72,
      "parents" : [113, 75],
      "spouse" : 130
    }, {
      "age" : 55,
      "alive" : true,
      "children" : [123, 124],
      "faction" : {
        "id" : 1,
        "occupation" : "fewterer",
        "title" : "Hunters"
      },
      "family" : 126,
      "friends" : [114, 94, 115, 125, 116],
      "gender" : true,
      "generation" : 2,
      "id" : 122,
      "lastName" : "Shakin",
      "name" : "Adam",
      "origFamily" : 126,
      "parents" : [],
      "spouse" : 114
    }, {
      "age" : 25,
      "alive" : false,
      "children" : [139, 140, 141],
      "faction" : {
        "id" : 1,
        "occupation" : "fewterer",
        "title" : "Hunters"
      },
      "family" : 109,
      "friends" : [119, 128, 127, 126, 130],
      "gender" : false,
      "generation" : 1,
      "id" : 123,
      "lastName" : "Pizzano",
      "name" : "Eleanore",
      "origFamily" : 126,
      "parents" : [114, 122],
      "spouse" : 106
    }, {
      "age" : 25,
      "alive" : true,
      "children" : [142, 143, 144],
      "faction" : {
        "id" : 0,
        "occupation" : "ackerman",
        "title" : "Farmers"
      },
      "family" : 126,
      "friends" : [121, 130, 126, 153],
      "gender" : true,
      "generation" : 1,
      "id" : 124,
      "lastName" : "Shakin",
      "name" : "Curtis",
      "origFamily" : 126,
      "parents" : [114, 122],
      "spouse" : 105
    }, {
      "age" : 59,
      "alive" : false,
      "children" : [126, 127, 128],
      "faction" : {
        "id" : 1,
        "occupation" : "sperviter",
        "title" : "Hunters"
      },
      "family" : 74,
      "friends" : [113, 122],
      "gender" : false,
      "generation" : 2,
      "id" : 125,
      "lastName" : "Siegal",
      "name" : "Ellen",
      "origFamily" : 129,
      "parents" : [],
      "spouse" : 115
    }, {
      "age" : 25,
      "alive" : true,
      "children" : [],
      "faction" : {
        "id" : 1,
        "occupation" : "sperviter",
        "title" : "Hunters"
      },
      "family" : 73,
      "friends" : [119, 130, 124, 123, 128],
      "gender" : false,
      "generation" : 1,
      "id" : 126,
      "lastName" : "Muramoto",
      "name" : "Charlotte",
      "origFamily" : 74,
      "parents" : [115, 125],
      "spouse" : 96
    }, {
      "age" : 21,
      "alive" : true,
      "children" : [145],
      "faction" : {
        "id" : 2,
        "occupation" : "combmaker",
        "title" : "Craftsmen"
      },
      "family" : 74,
      "friends" : [119, 131, 123, 120, 132],
      "gender" : true,
      "generation" : 1,
      "id" : 127,
      "lastName" : "Siegal",
      "name" : "Sam",
      "origFamily" : 74,
      "parents" : [115, 125],
      "spouse" : 91
    }, {
      "age" : 22,
      "alive" : true,
      "children" : [133, 134, 146, 147],
      "faction" : {
        "id" : 2,
        "occupation" : "combmaker",
        "title" : "Craftsmen"
      },
      "family" : 74,
      "friends" : [132, 123, 130, 120, 121, 126],
      "gender" : true,
      "generation" : 1,
      "id" : 128,
      "lastName" : "Siegal",
      "name" : "Vernon",
      "origFamily" : 74,
      "parents" : [115, 125],
      "spouse" : 119
    }, {
      "age" : 59,
      "alive" : false,
      "children" : [130, 131, 132],
      "faction" : {
        "id" : 2,
        "occupation" : "limner",
        "title" : "Craftsmen"
      },
      "family" : 133,
      "friends" : [116],
      "gender" : true,
      "generation" : 2,
      "id" : 129,
      "lastName" : "Kaplan",
      "name" : "Ralph",
      "origFamily" : 133,
      "parents" : [],
      "spouse" : 118
    }, {
      "age" : 24,
      "alive" : true,
      "children" : [136, 137, 138, 151, 152],
      "faction" : {
        "id" : 0,
        "occupation" : "horse trainer",
        "title" : "Farmers"
      },
      "family" : 133,
      "friends" : [128, 126, 124, 123],
      "gender" : true,
      "generation" : 1,
      "id" : 130,
      "lastName" : "Kaplan",
      "name" : "Gerald",
      "origFamily" : 133,
      "parents" : [118, 129],
      "spouse" : 121
    }, {
      "age" : 26,
      "alive" : false,
      "children" : [135, 154, 155, 156],
      "faction" : {
        "id" : 2,
        "occupation" : "limner",
        "title" : "Craftsmen"
      },
      "family" : 72,
      "friends" : [120, 127, 105, 91, 119, 148],
      "gender" : false,
      "generation" : 1,
      "id" : 131,
      "lastName" : "Shomo",
      "name" : "Roberta",
      "origFamily" : 133,
      "parents" : [118, 129],
      "spouse" : 120
    }, {
      "age" : 24,
      "alive" : true,
      "children" : [157],
      "faction" : {
        "id" : 2,
        "occupation" : "limner",
        "title" : "Craftsmen"
      },
      "family" : 157,
      "friends" : [128, 106, 105, 127, 148, 149, 150],
      "gender" : false,
      "generation" : 1,
      "id" : 132,
      "lastName" : "Symmes",
      "name" : "Victoria",
      "origFamily" : 133,
      "parents" : [118, 129],
      "spouse" : 153
    }, {
      "age" : 6,
      "alive" : true,
      "children" : [],
      "family" : 74,
      "friends" : [],
      "gender" : false,
      "generation" : 0,
      "id" : 133,
      "lastName" : "Siegal",
      "name" : "Marion",
      "origFamily" : 74,
      "parents" : [119, 128],
      "spouse" : -1
    }, {
      "age" : 6,
      "alive" : true,
      "children" : [],
      "family" : 74,
      "friends" : [],
      "gender" : true,
      "generation" : 0,
      "id" : 134,
      "lastName" : "Siegal",
      "name" : "Anthony",
      "origFamily" : 74,
      "parents" : [119, 128],
      "spouse" : -1
    }, {
      "age" : 10,
      "alive" : true,
      "children" : [],
      "family" : 72,
      "friends" : [],
      "gender" : true,
      "generation" : 0,
      "id" : 135,
      "lastName" : "Shomo",
      "name" : "Forest",
      "origFamily" : 72,
      "parents" : [120, 131],
      "spouse" : -1
    }, {
      "age" : 1,
      "alive" : true,
      "children" : [],
      "family" : 133,
      "friends" : [],
      "gender" : false,
      "generation" : 0,
      "id" : 136,
      "lastName" : "Kaplan",
      "name" : "Lillian",
      "origFamily" : 133,
      "parents" : [121, 130],
      "spouse" : -1
    }, {
      "age" : 4,
      "alive" : true,
      "children" : [],
      "family" : 133,
      "friends" : [],
      "gender" : true,
      "generation" : 0,
      "id" : 137,
      "lastName" : "Kaplan",
      "name" : "Vincent",
      "origFamily" : 133,
      "parents" : [121, 130],
      "spouse" : -1
    }, {
      "age" : 6,
      "alive" : true,
      "children" : [],
      "family" : 133,
      "friends" : [],
      "gender" : true,
      "generation" : 0,
      "id" : 138,
      "lastName" : "Kaplan",
      "name" : "Ernest",
      "origFamily" : 133,
      "parents" : [121, 130],
      "spouse" : -1
    }, {
      "age" : 4,
      "alive" : true,
      "children" : [],
      "family" : 109,
      "friends" : [],
      "gender" : true,
      "generation" : 0,
      "id" : 139,
      "lastName" : "Pizzano",
      "name" : "Edward",
      "origFamily" : 109,
      "parents" : [123, 106],
      "spouse" : -1
    }, {
      "age" : 5,
      "alive" : true,
      "children" : [],
      "family" : 109,
      "friends" : [],
      "gender" : true,
      "generation" : 0,
      "id" : 140,
      "lastName" : "Pizzano",
      "name" : "Judson",
      "origFamily" : 109,
      "parents" : [123, 106],
      "spouse" : -1
    }, {
      "age" : 9,
      "alive" : false,
      "children" : [],
      "family" : 109,
      "friends" : [],
      "gender" : true,
      "generation" : 0,
      "id" : 141,
      "lastName" : "Pizzano",
      "name" : "Lee",
      "origFamily" : 109,
      "parents" : [123, 106],
      "spouse" : -1
    }, {
      "age" : 1,
      "alive" : true,
      "children" : [],
      "family" : 126,
      "friends" : [],
      "gender" : true,
      "generation" : 0,
      "id" : 142,
      "lastName" : "Shakin",
      "name" : "Dwight",
      "origFamily" : 126,
      "parents" : [124, 105],
      "spouse" : -1
    }, {
      "age" : 9,
      "alive" : true,
      "children" : [],
      "family" : 126,
      "friends" : [],
      "gender" : false,
      "generation" : 0,
      "id" : 143,
      "lastName" : "Shakin",
      "name" : "Margaret",
      "origFamily" : 126,
      "parents" : [124, 105],
      "spouse" : -1
    }, {
      "age" : 9,
      "alive" : true,
      "children" : [],
      "family" : 126,
      "friends" : [],
      "gender" : true,
      "generation" : 0,
      "id" : 144,
      "lastName" : "Shakin",
      "name" : "Daniel",
      "origFamily" : 126,
      "parents" : [124, 105],
      "spouse" : -1
    }, {
      "age" : 5,
      "alive" : true,
      "children" : [],
      "family" : 74,
      "friends" : [],
      "gender" : false,
      "generation" : 0,
      "id" : 145,
      "lastName" : "Siegal",
      "name" : "Annie",
      "origFamily" : 74,
      "parents" : [127, 91],
      "spouse" : -1
    }, {
      "age" : 6,
      "alive" : true,
      "children" : [],
      "family" : 74,
      "friends" : [],
      "gender" : true,
      "generation" : 0,
      "id" : 146,
      "lastName" : "Siegal",
      "name" : "Leon",
      "origFamily" : 74,
      "parents" : [128, 119],
      "spouse" : -1
    }, {
      "age" : 6,
      "alive" : false,
      "children" : [],
      "family" : 74,
      "friends" : [],
      "gender" : true,
      "generation" : 0,
      "id" : 147,
      "lastName" : "Siegal",
      "name" : "Alvin",
      "origFamily" : 74,
      "parents" : [128, 119],
      "spouse" : -1
    }, {
      "age" : 37,
      "alive" : true,
      "children" : [],
      "family" : 152,
      "friends" : [121, 131, 120, 132],
      "gender" : false,
      "generation" : 1,
      "id" : 148,
      "lastName" : "Harres",
      "name" : "Harriet",
      "origFamily" : 152,
      "parents" : [],
      "spouse" : -1
    }, {
      "age" : 29,
      "alive" : false,
      "children" : [],
      "family" : 153,
      "friends" : [121, 132],
      "gender" : false,
      "generation" : 1,
      "id" : 149,
      "lastName" : "Lababit",
      "name" : "Dora",
      "origFamily" : 153,
      "parents" : [],
      "spouse" : -1
    }, {
      "age" : 28,
      "alive" : true,
      "children" : [],
      "family" : 154,
      "friends" : [121, 120, 132],
      "gender" : false,
      "generation" : 1,
      "id" : 150,
      "lastName" : "Kratochwil",
      "name" : "Olga",
      "origFamily" : 154,
      "parents" : [],
      "spouse" : -1
    }, {
      "age" : 5,
      "alive" : true,
      "children" : [],
      "family" : 133,
      "friends" : [],
      "gender" : true,
      "generation" : 0,
      "id" : 151,
      "lastName" : "Kaplan",
      "name" : "Forest",
      "origFamily" : 133,
      "parents" : [130, 121],
      "spouse" : -1
    }, {
      "age" : 8,
      "alive" : true,
      "children" : [],
      "family" : 133,
      "friends" : [],
      "gender" : true,
      "generation" : 0,
      "id" : 152,
      "lastName" : "Kaplan",
      "name" : "Kermit",
      "origFamily" : 133,
      "parents" : [130, 121],
      "spouse" : -1
    }, {
      "age" : 35,
      "alive" : false,
      "children" : [157],
      "faction" : {
        "id" : 0,
        "occupation" : "yeoman",
        "title" : "Farmers"
      },
      "family" : 157,
      "friends" : [124],
      "gender" : true,
      "generation" : 1,
      "id" : 153,
      "lastName" : "Symmes",
      "name" : "Dale",
      "origFamily" : 157,
      "parents" : [],
      "spouse" : 132
    }, {
      "age" : 10,
      "alive" : true,
      "children" : [],
      "family" : 72,
      "friends" : [],
      "gender" : true,
      "generation" : 0,
      "id" : 154,
      "lastName" : "Shomo",
      "name" : "Thomas",
      "origFamily" : 72,
      "parents" : [131, 120],
      "spouse" : -1
    }, {
      "age" : 10,
      "alive" : true,
      "children" : [],
      "family" : 72,
      "friends" : [],
      "gender" : true,
      "generation" : 0,
      "id" : 155,
      "lastName" : "Shomo",
      "name" : "Francis",
      "origFamily" : 72,
      "parents" : [131, 120],
      "spouse" : -1
    }, {
      "age" : 10,
      "alive" : true,
      "children" : [],
      "family" : 72,
      "friends" : [],
      "gender" : false,
      "generation" : 0,
      "id" : 156,
      "lastName" : "Shomo",
      "name" : "Geraldine",
      "origFamily" : 72,
      "parents" : [131, 120],
      "spouse" : -1
    }, {
      "age" : 0,
      "alive" : true,
      "children" : [],
      "family" : 157,
      "friends" : [],
      "gender" : false,
      "generation" : 0,
      "id" : 157,
      "lastName" : "Symmes",
      "name" : "Laura",
      "origFamily" : 157,
      "parents" : [132, 153],
      "spouse" : -1
    }]
}